tradingview_screener/__init__.py
tradingview_screener/constants.py
tradingview_screener/default_screeners.py
tradingview_screener/query.py
tradingview_screener/screener.py
tradingview_screener/util.py
tradingview_screener-2.5.0.dist-info/LICENSE
tradingview_screener-2.5.0.dist-info/METADATA
tradingview_screener-2.5.0.dist-info/WHEEL
tradingview_screener-2.5.0.dist-info/RECORD
