Metadata-Version: 2.1
Name: tradingview-screener
Version: 2.5.0
Summary: A package for creating stock screeners with the TradingView API
Home-page: https://github.com/shner-elmo/TradingView-Screener
License: MIT
Author: shner-elmo
Author-email: 770elmo@gmail.com
Requires-Python: >=3.9,<3.13
Classifier: Environment :: Console
Classifier: License :: OSI Approved :: MIT License
Classifier: Operating System :: OS Independent
Classifier: Programming Language :: Python
Classifier: Programming Language :: Python :: 3
Classifier: Programming Language :: Python :: 3.9
Classifier: Programming Language :: Python :: 3.10
Classifier: Programming Language :: Python :: 3.11
Classifier: Programming Language :: Python :: 3 :: Only
Requires-Dist: pandas (>=2.1.2,<3.0.0)
Requires-Dist: requests (>=2.31.0,<3.0.0)
Project-URL: Documentation, https://github.com/shner-elmo/TradingView-Screener/blob/master/README.md
Project-URL: Repository, https://github.com/shner-elmo/TradingView-Screener
